gha_python_packaging_test/__init__.py
gha_python_packaging_test/app.py
gha_python_packaging_test-0.0.7.dist-info/LICENSE
gha_python_packaging_test-0.0.7.dist-info/METADATA
gha_python_packaging_test-0.0.7.dist-info/WHEEL
gha_python_packaging_test-0.0.7.dist-info/entry_points.txt
gha_python_packaging_test-0.0.7.dist-info/top_level.txt
gha_python_packaging_test-0.0.7.dist-info/RECORD
