Metadata-Version: 2.1
Name: gha-python-packaging-test
Version: 0.0.7
Summary: Test project for our GitHub Actions Python packaging workflow
Home-page: https://github.com/hypothesis/gha-python-packaging-test
Project-URL: Bug Tracker, https://github.com/hypothesis/gha-python-packaging-test/issues
Project-URL: Changelog, https://github.com/hypothesis/gha-python-packaging-test/releases
Classifier: Programming Language :: Python :: 3
Classifier: License :: OSI Approved :: BSD License
Classifier: Intended Audience :: Developers
Requires-Python: >=3.6
License-File: LICENSE
